vegetablesclassify/__init__.py
vegetablesclassify/classify.py
vegetablesclassify-0.0.8.dist-info/METADATA
vegetablesclassify-0.0.8.dist-info/WHEEL
vegetablesclassify-0.0.8.dist-info/top_level.txt
vegetablesclassify-0.0.8.dist-info/RECORD
